censius/CensiusClient.py
censius/DatasetType.py
censius/ModelType.py
censius/__init__.py
censius/schemas.py
censius/utils.py
censius-0.2.1.dist-info/METADATA
censius-0.2.1.dist-info/WHEEL
censius-0.2.1.dist-info/top_level.txt
censius-0.2.1.dist-info/RECORD
