Metadata-Version: 2.1
Name: censius
Version: 0.2.1
Summary: API for Censius
Home-page: https://github.com/Censius/censius-logs-python-sdk
Author: Censius
Author-email: dev@censius.ai
License: UNKNOWN
Platform: UNKNOWN
Requires-Dist: requests
Provides-Extra: dev
Requires-Dist: pdoc3 (==0.9.2) ; extra == 'dev'
Requires-Dist: pytest (>=3.7) ; extra == 'dev'
